README.md
setup.py
x256_img.py
x256_img.egg-info/PKG-INFO
x256_img.egg-info/SOURCES.txt
x256_img.egg-info/dependency_links.txt
x256_img.egg-info/entry_points.txt
x256_img.egg-info/requires.txt
x256_img.egg-info/top_level.txt