Metadata-Version: 1.2
Name: x256-img
Version: 0.0.1
Summary: Display pictures in a terminal using x256 color codes
Home-page: UNKNOWN
Author: Jacob Jäger
Maintainer: Jacob Jäger
License: UNKNOWN
Platform: UNKNOWN
Classifier: Development Status :: 3 - Alpha
Classifier: License :: OSI Approved :: MIT License
Classifier: Natural Language :: English
Classifier: Operating System :: OS Independent
Classifier: Programming Language :: Python :: 3 :: Only
